<?xml version="1.0" encoding="UTF-8" standalone="no" ?><CAERep ObjId="60" Type="CAERep" Ver="2"><DSEnvironmentID PropType="int">28</DSEnvironmentID><Goal PropType="string">RunSolver</Goal><HasBetaKeyOn PropType="bool">false</HasBetaKeyOn><InProcess PropType="bool">true</InProcess><LastDatabaseId PropType="unsigned int">105</LastDatabaseId><NumProcessorsForPost PropType="int">0</NumProcessorsForPost><PID_Legacy_Solve PropType="int">0</PID_Legacy_Solve><PartialCode PropType="int">1</PartialCode><ProductVersion PropType="string">15.0.7  Release</ProductVersion><ProductVersionForSec PropType="string">15.0</ProductVersionForSec><ProjectName PropType="string">cylinder--Static Structural (A5)</ProjectName><ReturnCode PropType="int">1</ReturnCode><SolveInvokedFromAddin PropType="int">0</SolveInvokedFromAddin><SysvarMap PropType="map&lt;string,string>"><Entry key="DSSolver ProgId">AMKSolver.AMKSolver.150</Entry></SysvarMap><EngineeringRep ObjId="61" Type="EngineeringRep" Ver="2"><BCRep ObjId="64" Type="BCRep" Ver="2"><StepEndTimes PropType="vector&lt;double>" UCat="Time" Unt="s">    1</StepEndTimes><ContactRep ObjId="25" Type="ContactRep" Ver="2"><Behavior PropType="string">ProgramControlled</Behavior><Breakable PropType="string">No</Breakable><Caption PropType="string">Frictionless - Solid To Solid</Caption><ContactCorrection PropType="string">NoCorrection</ContactCorrection><DampingFactor PropType="double">    0</DampingFactor><DecayConstant PropType="double">    0</DecayConstant><DetectionMethod PropType="string">ProgramControlled</DetectionMethod><DynamicCoefficient PropType="double">    0</DynamicCoefficient><Formulation PropType="string">ProgramControlledContact</Formulation><InitialEffect PropType="string">AddOffsetNoRamp</InitialEffect><MaximumOffset PropType="double" UCat="Length" Unt="m">1e-007</MaximumOffset><Restitution PropType="double">    1</Restitution><Scoping PropType="vector&lt;string>">26,27</Scoping><SourceBodyIds PropType="vector&lt;unsigned int>">28,28,28</SourceBodyIds><StaticCoefficient PropType="double">    0</StaticCoefficient><TargetBodyIds PropType="vector&lt;unsigned int>">99,99,99</TargetBodyIds><TargetCorrection PropType="string">NoCorrection</TargetCorrection><TimeStepControls PropType="string">NoPrediction</TimeStepControls><TrimTolerance PropType="double" Unt="mm">2.82644224381454</TrimTolerance><TrimType PropType="string">ProgramControlled</TrimType><Type PropType="string">Frictionless</Type><UseAutoPenetrationTolerance PropType="string">ProgramControlled</UseAutoPenetrationTolerance><UserOffset PropType="double" UCat="Length" Unt="mm">    0</UserOffset><SourceReference ObjId="87" Type="CAERepBase" Ver="2"><ReferenceId PropType="unsigned int">38</ReferenceId><ReferenceType PropType="vector&lt;string>">Cylinder,Face,RightCylinder</ReferenceType></SourceReference><SourceReference ObjId="88" Type="CAERepBase" Ver="2"><ReferenceId PropType="unsigned int">37</ReferenceId><ReferenceType PropType="vector&lt;string>">Face,Plane</ReferenceType></SourceReference><SourceReference ObjId="89" Type="CAERepBase" Ver="2"><ReferenceId PropType="unsigned int">32</ReferenceId><ReferenceType PropType="vector&lt;string>">Cylinder,Face,RightCylinder</ReferenceType></SourceReference><TargetReference ObjId="90" Type="CAERepBase" Ver="2"><ReferenceId PropType="unsigned int">109</ReferenceId><ReferenceType PropType="vector&lt;string>">Cylinder,Face,RightCylinder</ReferenceType></TargetReference><TargetReference ObjId="91" Type="CAERepBase" Ver="2"><ReferenceId PropType="unsigned int">119</ReferenceId><ReferenceType PropType="vector&lt;string>">Face,Plane</ReferenceType></TargetReference><TargetReference ObjId="92" Type="CAERepBase" Ver="2"><ReferenceId PropType="unsigned int">108</ReferenceId><ReferenceType PropType="vector&lt;string>">Cylinder,Face,RightCylinder</ReferenceType></TargetReference><Pinball ObjId="86" Type="Pinball" Ver="2"><Type PropType="string">ProgramControlled</Type></Pinball><ProgramControlledContact ObjId="85" Type="ProgramControlledContact" Ver="2"><UpdateStiffness PropType="string">Never</UpdateStiffness><UseAutoElectricalConductance PropType="bool">true</UseAutoElectricalConductance><UseAutoNormalStiffness PropType="bool">true</UseAutoNormalStiffness><UseAutoThermalConductance PropType="bool">true</UseAutoThermalConductance></ProgramControlledContact></ContactRep><SurfaceDisplacement ObjId="37" Type="DisplacementConstraint" Ver="1"><Caption PropType="string">Displacement</Caption><RefCoordSysId PropType="unsigned int">23</RefCoordSysId><Scoping PropType="vector&lt;string>">38</Scoping><LoadStep ObjId="93" Type="LoadStep" Ver="2"><IsActive PropType="vector&lt;bool>">true</IsActive><Number PropType="vector&lt;int>"/></LoadStep><ComponentX ObjId="94" Type="Table" Ver="2"><StepNumber PropType="vector&lt;int>">1,1</StepNumber><Time PropType="vector&lt;double>" UCat="Time" Unt="s">    0,    1</Time><Values PropType="vector&lt;double>" UCat="Displacement" Unt="mm">    0,    0</Values></ComponentX><ComponentZ ObjId="95" Type="Table" Ver="2"><StepNumber PropType="vector&lt;int>">1,1</StepNumber><Time PropType="vector&lt;double>" UCat="Time" Unt="s">    0,    1</Time><Values PropType="vector&lt;double>" UCat="Displacement" Unt="mm">    0,    0</Values></ComponentZ></SurfaceDisplacement><EdgeForce ObjId="39" Type="Force" Ver="2"><Caption PropType="string">Force</Caption><RefCoordSysId PropType="unsigned int">23</RefCoordSysId><Scoping PropType="vector&lt;string>">40</Scoping><LoadStep ObjId="96" Type="LoadStep" Ver="2"><IsActive PropType="vector&lt;bool>">true</IsActive><Number PropType="vector&lt;int>"/></LoadStep><ComponentX ObjId="97" Type="Table" Ver="2"><StepNumber PropType="vector&lt;int>">1,1</StepNumber><Time PropType="vector&lt;double>" UCat="Time" Unt="s">    0,    1</Time><Values PropType="vector&lt;double>" UCat="Force" Unt="tonne mm s^-2">    0,    0</Values></ComponentX><ComponentY ObjId="98" Type="Table" Ver="2"><StepNumber PropType="vector&lt;int>">1,1</StepNumber><Time PropType="vector&lt;double>" UCat="Time" Unt="s">    0,    1</Time><Values PropType="vector&lt;double>" UCat="Force" Unt="tonne mm s^-2">    0,    0</Values></ComponentY><ComponentZ ObjId="99" Type="Table" Ver="2"><StepNumber PropType="vector&lt;int>">1,1</StepNumber><Time PropType="vector&lt;double>" UCat="Time" Unt="s">    0,    1</Time><Values PropType="vector&lt;double>" UCat="Force" Unt="tonne mm s^-2">    0, 1000</Values></ComponentZ></EdgeForce><FrictionlessSupport ObjId="35" Type="Support" Ver="2"><Caption PropType="string">Frictionless Support</Caption><Scoping PropType="vector&lt;string>">36</Scoping><Type PropType="string"/></FrictionlessSupport></BCRep><GeometryAttributes ObjId="62" Type="GeometryAttributes" Ver="2"><AssemblyAttributes ObjId="63" Type="AssemblyAttributes" Ver="2"><ElementOptionControl PropType="string">ProgramControlled</ElementOptionControl><GeometrySource PropType="string">C:\Users\petr\AppData\Local\Temp\WB_PETER_petr_8184_2\unsaved_project_files\dp0\SYS\DM\SYS.agdb</GeometrySource><Is2DAnalysis PropType="bool">false</Is2DAnalysis><PartAttributes ObjId="15" Type="PartAttributes" Ver="2"><Caption PropType="string">Solid Bodies</Caption><Mass PropType="double" UCat="Mass" Unt="tonne">0.01236222993724409</Mass><PartId PropType="unsigned int">3</PartId><BodyAttributes ObjId="16" Type="BodyAttributes" Ver="2"><AreNonLinearEffectsOn PropType="bool">true</AreNonLinearEffectsOn><BoundingBoxDiagonal PropType="double" UCat="Length" Unt="mm">604.9660124862221</BoundingBoxDiagonal><Caption PropType="string">Solid</Caption><ElementCoordSysId PropType="unsigned int">23</ElementCoordSysId><GeometryType PropType="string">Solid</GeometryType><Mass PropType="double" UCat="Mass" Unt="tonne">0.01236222993724409</Mass><ProtoReferenceId PropType="unsigned int">28</ProtoReferenceId><StiffnessBehavior PropType="string">Deformable</StiffnessBehavior><ThermalStrainCalculation PropType="bool">true</ThermalStrainCalculation><MassMomentOfInertia ObjId="75" Type="MassMomentOfInertia" Ver="2"><Ixx PropType="double" UCat="MomentInertiaMass" Unt="tonne mm^2">324.4313642460215</Ixx><Iyy PropType="double" UCat="MomentInertiaMass" Unt="tonne mm^2">23.55530894473503</Iyy><Izz PropType="double" UCat="MomentInertiaMass" Unt="tonne mm^2">324.3831700800737</Izz></MassMomentOfInertia><MaterialRep ObjId="74" Type="MaterialRep" Ver="2"><MaterialName PropType="string">Structural Steel</MaterialName><ReferenceTemperature PropType="double" UCat="Temperature" Unt="Celsius">   22</ReferenceTemperature><UnitSystem PropType="int">0</UnitSystem><UseReferenceTemperature PropType="bool">false</UseReferenceTemperature></MaterialRep><Centroid ObjId="76" Type="Point3D" Ver="3"><Coordinates PropType="vector&lt;double>" UCat="Length" Unt="mm">2.483212230945367e-015,252.3685573665539,5.218405748364216e-015</Coordinates></Centroid></BodyAttributes><MassMomentOfInertia ObjId="70" Type="MassMomentOfInertia" Ver="2"><Ixx PropType="double" UCat="MomentInertiaMass" Unt="tonne mm^2">324.4313642460215</Ixx><Iyy PropType="double" UCat="MomentInertiaMass" Unt="tonne mm^2">23.55530894473503</Iyy><Izz PropType="double" UCat="MomentInertiaMass" Unt="tonne mm^2">324.3831700800737</Izz><CoordinateSystemRep ObjId="71" Type="CoordinateSystemRep" Ver="3"><Caption PropType="string">Undefined</Caption><IsGlobal PropType="bool">false</IsGlobal><Param1 PropType="double">    1</Param1><Param2 PropType="double">    1</Param2><Singularity1 PropType="int">0</Singularity1><Singularity2 PropType="int">0</Singularity2><SolverCoordNumber PropType="unsigned int">0</SolverCoordNumber><Type PropType="string">Cartesian</Type><Matrix3X3 ObjId="72" Type="Matrix3X3" Ver="2"><IsOrthogonal PropType="bool">false</IsOrthogonal><Row0 PropType="vector&lt;double>">    1,    0,    0</Row0><Row1 PropType="vector&lt;double>">    0,    1,    0</Row1><Row2 PropType="vector&lt;double>">    0,    0,    1</Row2></Matrix3X3><Point3D ObjId="73" Type="Point3D" Ver="3"><Coordinates PropType="vector&lt;double>" UCat="Length" Unt="mm">2.483212230945367e-015,252.3685573665539,5.218405748364216e-015</Coordinates></Point3D></CoordinateSystemRep></MassMomentOfInertia><Centroid ObjId="69" Type="Point3D" Ver="3"><Coordinates PropType="vector&lt;double>" UCat="Length" Unt="mm">2.483212230945367e-015,252.3685573665539,5.218405748364216e-015</Coordinates></Centroid></PartAttributes><PartAttributes ObjId="18" Type="PartAttributes" Ver="2"><Caption PropType="string">Solid Bodies</Caption><Mass PropType="double" UCat="Mass" Unt="tonne">0.007997552566976823</Mass><PartId PropType="unsigned int">5</PartId><BodyAttributes ObjId="19" Type="BodyAttributes" Ver="2"><AreNonLinearEffectsOn PropType="bool">true</AreNonLinearEffectsOn><BoundingBoxDiagonal PropType="double" UCat="Length" Unt="mm">614.0063570979988</BoundingBoxDiagonal><Caption PropType="string">Solid</Caption><ElementCoordSysId PropType="unsigned int">23</ElementCoordSysId><GeometryType PropType="string">Solid</GeometryType><Mass PropType="double" UCat="Mass" Unt="tonne">0.007997552566976823</Mass><ProtoReferenceId PropType="unsigned int">99</ProtoReferenceId><StiffnessBehavior PropType="string">Deformable</StiffnessBehavior><ThermalStrainCalculation PropType="bool">true</ThermalStrainCalculation><MassMomentOfInertia ObjId="83" Type="MassMomentOfInertia" Ver="2"><Ixx PropType="double" UCat="MomentInertiaMass" Unt="tonne mm^2">238.4025236590836</Ixx><Iyy PropType="double" UCat="MomentInertiaMass" Unt="tonne mm^2">3.371884894009322</Iyy><Izz PropType="double" UCat="MomentInertiaMass" Unt="tonne mm^2">238.3381456690625</Izz></MassMomentOfInertia><MaterialRep ObjId="82" Type="MaterialRep" Ver="2"><MaterialName PropType="string">Structural Steel</MaterialName><ReferenceTemperature PropType="double" UCat="Temperature" Unt="Celsius">   22</ReferenceTemperature><UnitSystem PropType="int">0</UnitSystem><UseReferenceTemperature PropType="bool">false</UseReferenceTemperature></MaterialRep><Centroid ObjId="84" Type="Point3D" Ver="3"><Coordinates PropType="vector&lt;double>" UCat="Length" Unt="mm">-1.997496594781831e-015,712.4847461537543,-3.15864929457217e-005</Coordinates></Centroid></BodyAttributes><MassMomentOfInertia ObjId="78" Type="MassMomentOfInertia" Ver="2"><Ixx PropType="double" UCat="MomentInertiaMass" Unt="tonne mm^2">238.4025236590836</Ixx><Iyy PropType="double" UCat="MomentInertiaMass" Unt="tonne mm^2">3.371884894009322</Iyy><Izz PropType="double" UCat="MomentInertiaMass" Unt="tonne mm^2">238.3381456690625</Izz><CoordinateSystemRep ObjId="79" Type="CoordinateSystemRep" Ver="3"><Caption PropType="string">Undefined</Caption><IsGlobal PropType="bool">false</IsGlobal><Param1 PropType="double">    1</Param1><Param2 PropType="double">    1</Param2><Singularity1 PropType="int">0</Singularity1><Singularity2 PropType="int">0</Singularity2><SolverCoordNumber PropType="unsigned int">0</SolverCoordNumber><Type PropType="string">Cartesian</Type><Matrix3X3 ObjId="80" Type="Matrix3X3" Ver="2"><IsOrthogonal PropType="bool">false</IsOrthogonal><Row0 PropType="vector&lt;double>">    1,-8.024795109654734e-015,8.831916639160533e-009</Row0><Row1 PropType="vector&lt;double>">1.106132980931597e-014,0.9999999999999409,-3.438137862621781e-007</Row1><Row2 PropType="vector&lt;double>">-8.83191663915725e-009,3.438137862621782e-007,0.9999999999999409</Row2></Matrix3X3><Point3D ObjId="81" Type="Point3D" Ver="3"><Coordinates PropType="vector&lt;double>" UCat="Length" Unt="mm">-1.997496594781831e-015,712.4847461537543,-3.15864929457217e-005</Coordinates></Point3D></CoordinateSystemRep></MassMomentOfInertia><Centroid ObjId="77" Type="Point3D" Ver="3"><Coordinates PropType="vector&lt;double>" UCat="Length" Unt="mm">-1.997496594781831e-015,712.4847461537543,-3.15864929457217e-005</Coordinates></Centroid></PartAttributes></AssemblyAttributes></GeometryAttributes><ServiceRep ObjId="65" Type="ServiceRep" Ver="2"><CoordinateSystemRep ObjId="23" Type="CoordinateSystemRep" Ver="3"><Caption PropType="string">Global Coordinate System</Caption><IsGlobal PropType="bool">true</IsGlobal><Param1 PropType="double">    1</Param1><Param2 PropType="double">    1</Param2><Singularity1 PropType="int">0</Singularity1><Singularity2 PropType="int">0</Singularity2><SolverCoordNumber PropType="int">0</SolverCoordNumber><Type PropType="string">Cartesian</Type><Matrix3X3 ObjId="100" Type="Matrix3X3" Ver="2"><IsOrthogonal PropType="bool">false</IsOrthogonal><Row0 PropType="vector&lt;double>">    1,    0,    0</Row0><Row1 PropType="vector&lt;double>">    0,    1,    0</Row1><Row2 PropType="vector&lt;double>">    0,    0,    1</Row2></Matrix3X3><Point3D ObjId="101" Type="Point3D" Ver="3"><Coordinates PropType="vector&lt;double>" UCat="Length" Unt="mm">    0,    0,    0</Coordinates></Point3D></CoordinateSystemRep><ReferenceDataRep ObjId="102" Type="ReferenceDataRep" Ver="2"><BodyId PropType="vector&lt;unsigned int>">28,99,28,28,28,99,99,99,28,99,99</BodyId><PartId PropType="vector&lt;unsigned int>">3,5,3,3,3,5,5,5,3,5,5</PartId><RefId PropType="vector&lt;unsigned int>">1,2,3,4,5,6,7,8,10,11,14</RefId><RefType PropType="vector&lt;unsigned int>">1048576,1048576,4256,96,4256,4256,96,4256,4256,4256,81920</RefType><RefValue PropType="vector&lt;unsigned int>">28,99,38,37,32,109,119,108,29,102,94</RefValue><Scoping PropType="vector&lt;string>">17,20,26,26,26,27,27,27,36,38,40</Scoping><Type PropType="vector&lt;unsigned int>">1,1,1,1,1,1,1,1,1,1,1</Type><UBID PropType="vector&lt;unsigned int>">16,19,16,16,16,19,19,19,16,19,19</UBID><UPID PropType="vector&lt;unsigned int>">15,18,15,15,15,18,18,18,15,18,18</UPID></ReferenceDataRep></ServiceRep></EngineeringRep><GeometryRep ObjId="68" Type="GeometryRep" Ver="2"><ActiveAssembly PropType="unsigned int">1</ActiveAssembly><PartsAssembly PropType="string">0000000001D14DD0</PartsAssembly><Units PropType="string">m</Units></GeometryRep><MaterialLibraryRep ObjId="67" Type="MaterialLibraryRep" Ver="2"><FileName PropType="string">MatML.xml</FileName></MaterialLibraryRep><MeshRep ObjId="66" Type="MeshRep" Ver="2"><AssemblyMesh PropType="string">000000001DCF0638</AssemblyMesh><Configuration PropType="unsigned int">33</Configuration><Units PropType="string">m</Units></MeshRep><SolverRep ObjId="103" Type="SolverRep" Ver="2"><AnalysisType PropType="string">Static</AnalysisType><PhysicsType PropType="string">Mechanical</PhysicsType><SolverTargetName PropType="string">ANSYS</SolverTargetName><SolverUnits PropType="int">6</SolverUnits><FEConnectorsRep ObjId="30" Type="FEConnectorsRep" Ver="2"><Caption PropType="string">FEConnectorsRep</Caption><ColorOption PropType="int">0</ColorOption><ComponentId PropType="int">0</ComponentId><DisplayOption PropType="int">0</DisplayOption><DisplayType PropType="string">Lines</DisplayType><LineColor PropType="int">14090455</LineColor><LineThickness PropType="int">0</LineThickness><ShowOnResults PropType="bool">false</ShowOnResults><StepNumber PropType="int">1</StepNumber><StepSelection PropType="int">0</StepSelection></FEConnectorsRep><FileManagementRep ObjId="105" Type="FileManagementRep" Ver="2"><ResultFileName PropType="string"/><SolverFileDirectory PropType="string"/><SolverFileRelativeDirectory PropType="string"/><UnitSystem PropType="int">6</UnitSystem></FileManagementRep><ProcessControls ObjId="104" Type="ProcessControls" Ver="2"><DistributedSolve PropType="bool">false</DistributedSolve><ManualMemorySettings PropType="bool">false</ManualMemorySettings><MaxProcessors PropType="int">2</MaxProcessors></ProcessControls><AnalysisSettings CAEType="extObj"><StaticMechanicalSettings version="1.0"><StepControls version="1.0"><EndTime>1.</EndTime><TimeStepOptions version="1.0"><AutoTimeSteppingType>ProgramControlled</AutoTimeSteppingType></TimeStepOptions><NonlinearControls version="1.0"><Force><ProgramControlled/></Force><Moment><ProgramControlled/></Moment><Rotation><ProgramControlled/></Rotation><Displacement><ProgramControlled/></Displacement><LineSearch>ProgramControlled</LineSearch><StabilizationControls><StabilizationControls version="1.0"><Controls>Off</Controls><Method>Energy</Method><EnergyDissipationRatio>1.e-004</EnergyDissipationRatio><DampingFactor>0.</DampingFactor><FirstSubstepOption>No</FirstSubstepOption><ForceLimit>0.2</ForceLimit></StabilizationControls></StabilizationControls></NonlinearControls><OutputControls version="1.0"><Stress>true</Stress><Strain>true</Strain><Contact>false</Contact><TimePointsOptions>All</TimePointsOptions><MaxNumberofResultSets>1000</MaxNumberofResultSets><GeneralMisc>false</GeneralMisc><CalculateFracture>false</CalculateFracture><ResultSetsType>Auto</ResultSetsType><CacheResultsInMemoryType>Never</CacheResultsInMemoryType><StoreModalResult>ProgramControlled</StoreModalResult><ExpandResultFrom>ProgramControlled</ExpandResultFrom><ProgControlledExpansion>Unknown</ProgControlledExpansion><NodalForcesType>No</NodalForcesType><ResultSets></ResultSets></OutputControls><CreepControls version="1.0"><CreepActivation/><CreepLimitRatio>1.</CreepLimitRatio></CreepControls><InertialRelief>false</InertialRelief></StepControls><SolverControls version="1.0"><SolverType><ProgramControlled/></SolverType><UseLargeDeformation>false</UseLargeDeformation><WeakSprings><ProgramControlled/></WeakSprings><FractureSolution>true</FractureSolution><NewtonRaphsonType><ProgramControlled/></NewtonRaphsonType></SolverControls><SolverFileControls version="1.0"><SolverEngineType>ANSYS</SolverEngineType><SolverUnits>6</SolverUnits><SolverFilesDirectory>C:\Users\petr\Desktop\cylinder_files\dp0\SYS\MECH\</SolverFilesDirectory><ScratchSolverFilesDirectory>C:\Users\petr\Desktop\_ProjectScratch\Scr2C68\</ScratchSolverFilesDirectory><AdditionalList/><SaveANSYSDB>false</SaveANSYSDB><DeleteUnusedFiles>true</DeleteUnusedFiles><ResultFile>file.rst</ResultFile></SolverFileControls><RestartAnalysis version="1.0"><RestartType>ProgramControlled</RestartType><RestartAction>ContinueAnalysis</RestartAction><RestartAtLoadStep>0</RestartAtLoadStep><RestartAtSubstep>0</RestartAtSubstep><RestartAtTime>0.000000000000000</RestartAtTime><EndStepTime>0.000000000000000</EndStepTime><ModifiedLoads></ModifiedLoads></RestartAnalysis><RestartControls version="1.0"><Controls>ProgramControlled</Controls><SaveAtLoadStep>None</SaveAtLoadStep><SaveAtSubstep>None</SaveAtSubstep><SaveSubstepFrequency>1</SaveSubstepFrequency><SaveMaximumFiles>0</SaveMaximumFiles><RetainFiles>No</RetainFiles></RestartControls><FractureControls version="1.0"/></StaticMechanicalSettings></AnalysisSettings></SolverRep></CAERep>